jbof.py
jbof-0.1.2.dist-info/LICENSE
jbof-0.1.2.dist-info/METADATA
jbof-0.1.2.dist-info/WHEEL
jbof-0.1.2.dist-info/top_level.txt
jbof-0.1.2.dist-info/RECORD
