Metadata-Version: 2.1
Name: jbof
Version: 0.1.2
Summary: A Daset from Just a Bunch of Files
Home-page: https://github.com/bastibe/jbof
Author: Bastian Bechtold
Author-email: basti@bastibe.de
License: GPL v3
Platform: UNKNOWN
Requires-Python: >=3.6
Requires-Dist: numpy
Requires-Dist: soundfile
Requires-Dist: scipy
